{"properties": {"id": 115215, "unknown_19": 0, "width": 4, "length": 4, "standard_object_is_blocking": false, "scaleX": 256, "scaleY": 256, "scaleZ": 256, "textures": [{"original": 11807, "replacement": 12185}], "models": [{"type": 10, "values": [84434]}], "occludes_2": false}, "uniques": [{"width": 4, "length": 4, "id": 115215, "unknown_19": 0, "standard_object_is_blocking": false, "scaleX": 256, "scaleY": 256, "scaleZ": 256, "textures": [{"original": 11807, "replacement": 12185}], "models": [{"type": 10, "values": [84434]}], "occludes_2": false, "plane": 0, "i": 57, "j": 49, "x": 35, "y": 61, "type": 10, "rotation": 1}]}