{"properties": {"id": 12290, "unknown_24": 3412, "ambient": 25, "contrast": 15, "unknown_21": true, "model": false, "unknown_88": false, "floor_decoration_object_is_walkable": false, "actions": ["Chop"], "models": [{"type": 10, "values": [10228]}], "name": "Jade root (healthy)", "action_cursors": [59], "occludes_2": false}, "uniques": [{"plane": 0, "i": 47, "j": 144, "x": 22, "y": 8, "id": 12290, "type": 10, "rotation": 2}, {"plane": 0, "i": 47, "j": 144, "x": 22, "y": 10, "id": 12290, "type": 10, "rotation": 3}, {"plane": 0, "i": 47, "j": 144, "x": 24, "y": 7, "id": 12290, "type": 10, "rotation": 1}, {"plane": 0, "i": 47, "j": 144, "x": 28, "y": 7, "id": 12290, "type": 10, "rotation": 3}, {"plane": 0, "i": 47, "j": 144, "x": 30, "y": 8, "id": 12290, "type": 10, "rotation": 2}, {"plane": 0, "i": 47, "j": 144, "x": 30, "y": 10, "id": 12290, "type": 10, "rotation": 1}]}