{"properties": {"id": 3893, "unknown_21": true, "models": [{"type": 10, "values": [3940]}], "name": "Stump", "occludes_2": false}, "uniques": [{"width": 1, "length": 1, "id": 3893, "unknown_21": true, "models": [{"type": 10, "values": [3940]}], "name": "Stump", "occludes_2": false, "plane": 0, "i": 33, "j": 49, "x": 61, "y": 13, "type": 10, "rotation": 3}, {"width": 1, "length": 1, "id": 3893, "unknown_21": true, "models": [{"type": 10, "values": [3940]}], "name": "Stump", "occludes_2": false, "plane": 0, "i": 33, "j": 49, "x": 62, "y": 54, "type": 10, "rotation": 2}, {"width": 1, "length": 1, "id": 3893, "unknown_21": true, "models": [{"type": 10, "values": [3940]}], "name": "Stump", "occludes_2": false, "plane": 0, "i": 35, "j": 50, "x": 49, "y": 56, "type": 10, "rotation": 2}]}