{"properties": {"id": 71368, "unknown_19": 0, "unknown_21": true, "ambient": 25, "contrast": 15, "unknown_88": false, "mirror": true, "textures": [{"original": 1512, "replacement": 1492}, {"original": 1529, "replacement": 1470}], "models": [{"type": 0, "values": [70076]}, {"type": 1, "values": [70071]}, {"type": 9, "values": [70094]}]}, "uniques": [{"width": 1, "length": 1, "id": 71368, "unknown_19": 0, "unknown_21": true, "ambient": 25, "contrast": 15, "unknown_88": false, "mirror": true, "textures": [{"original": 1512, "replacement": 1492}, {"original": 1529, "replacement": 1470}], "models": [{"type": 0, "values": [70076]}, {"type": 1, "values": [70071]}, {"type": 9, "values": [70094]}], "plane": 0, "i": 17, "j": 95, "x": 35, "y": 21, "type": 0, "rotation": 1}, {"width": 1, "length": 1, "id": 71368, "unknown_19": 0, "unknown_21": true, "ambient": 25, "contrast": 15, "unknown_88": false, "mirror": true, "textures": [{"original": 1512, "replacement": 1492}, {"original": 1529, "replacement": 1470}], "models": [{"type": 0, "values": [70076]}, {"type": 1, "values": [70071]}, {"type": 9, "values": [70094]}], "plane": 0, "i": 22, "j": 95, "x": 26, "y": 43, "type": 0, "rotation": 3}, {"width": 1, "length": 1, "id": 71368, "unknown_19": 0, "unknown_21": true, "ambient": 25, "contrast": 15, "unknown_88": false, "mirror": true, "textures": [{"original": 1512, "replacement": 1492}, {"original": 1529, "replacement": 1470}], "models": [{"type": 0, "values": [70076]}, {"type": 1, "values": [70071]}, {"type": 9, "values": [70094]}], "plane": 0, "i": 22, "j": 95, "x": 35, "y": 26, "type": 0, "rotation": 1}, {"width": 1, "length": 1, "id": 71368, "unknown_19": 0, "unknown_21": true, "ambient": 25, "contrast": 15, "unknown_88": false, "mirror": true, "textures": [{"original": 1512, "replacement": 1492}, {"original": 1529, "replacement": 1470}], "models": [{"type": 0, "values": [70076]}, {"type": 1, "values": [70071]}, {"type": 9, "values": [70094]}], "plane": 0, "i": 22, "j": 97, "x": 26, "y": 43, "type": 0, "rotation": 3}, {"width": 1, "length": 1, "id": 71368, "unknown_19": 0, "unknown_21": true, "ambient": 25, "contrast": 15, "unknown_88": false, "mirror": true, "textures": [{"original": 1512, "replacement": 1492}, {"original": 1529, "replacement": 1470}], "models": [{"type": 0, "values": [70076]}, {"type": 1, "values": [70071]}, {"type": 9, "values": [70094]}], "plane": 0, "i": 22, "j": 97, "x": 35, "y": 26, "type": 0, "rotation": 1}, {"width": 1, "length": 1, "id": 71368, "unknown_19": 0, "unknown_21": true, "ambient": 25, "contrast": 15, "unknown_88": false, "mirror": true, "textures": [{"original": 1512, "replacement": 1492}, {"original": 1529, "replacement": 1470}], "models": [{"type": 0, "values": [70076]}, {"type": 1, "values": [70071]}, {"type": 9, "values": [70094]}], "plane": 0, "i": 53, "j": 111, "x": 26, "y": 43, "type": 0, "rotation": 3}, {"width": 1, "length": 1, "id": 71368, "unknown_19": 0, "unknown_21": true, "ambient": 25, "contrast": 15, "unknown_88": false, "mirror": true, "textures": [{"original": 1512, "replacement": 1492}, {"original": 1529, "replacement": 1470}], "models": [{"type": 0, "values": [70076]}, {"type": 1, "values": [70071]}, {"type": 9, "values": [70094]}], "plane": 0, "i": 53, "j": 111, "x": 35, "y": 26, "type": 0, "rotation": 1}]}